creality_k1_api/__init__.py
creality_k1_api/client.py
creality_k1_api-0.0.1.dist-info/LICENSE
creality_k1_api-0.0.1.dist-info/METADATA
creality_k1_api-0.0.1.dist-info/WHEEL
creality_k1_api-0.0.1.dist-info/top_level.txt
creality_k1_api-0.0.1.dist-info/RECORD
