Metadata-Version: 2.1
Name: creality-k1-api
Version: 0.0.1
Summary: A Python API for the Creality K1 3D printer
Home-page: https://github.com/hurricaneb/creality_k1_api
Author: hurricaneb
Author-email: hurricaneb@gmail.com
Classifier: Programming Language :: Python :: 3
Classifier: License :: OSI Approved :: GNU General Public License v3 (GPLv3)
Classifier: Operating System :: OS Independent
Requires-Python: >=3.6
License-File: LICENSE
Requires-Dist: websockets
